.coveragerc
.pylintrc
.testr.conf
AUTHORS
CONTRIBUTING.rst
ChangeLog
HACKING.rst
LICENSE
MANIFEST.in
README.rst
babel.cfg
neutron_test.sh
requirements.txt
setup.cfg
setup.py
test-requirements.txt
tox.ini
doc/source/conf.py
doc/source/index.rst
doc/source/devref/cli_option_guideline.rst
doc/source/devref/client_command_extensions.rst
doc/source/devref/transition_to_osc.rst
doc/source/usage/cli.rst
doc/source/usage/library.rst
neutronclient/__init__.py
neutronclient/_i18n.py
neutronclient/client.py
neutronclient/i18n.py
neutronclient/shell.py
neutronclient/version.py
neutronclient/common/__init__.py
neutronclient/common/clientmanager.py
neutronclient/common/constants.py
neutronclient/common/exceptions.py
neutronclient/common/extension.py
neutronclient/common/serializer.py
neutronclient/common/utils.py
neutronclient/common/validators.py
neutronclient/neutron/__init__.py
neutronclient/neutron/client.py
neutronclient/neutron/v2_0/__init__.py
neutronclient/neutron/v2_0/address_scope.py
neutronclient/neutron/v2_0/agent.py
neutronclient/neutron/v2_0/agentscheduler.py
neutronclient/neutron/v2_0/auto_allocated_topology.py
neutronclient/neutron/v2_0/availability_zone.py
neutronclient/neutron/v2_0/dns.py
neutronclient/neutron/v2_0/extension.py
neutronclient/neutron/v2_0/floatingip.py
neutronclient/neutron/v2_0/metering.py
neutronclient/neutron/v2_0/network.py
neutronclient/neutron/v2_0/network_ip_availability.py
neutronclient/neutron/v2_0/port.py
neutronclient/neutron/v2_0/purge.py
neutronclient/neutron/v2_0/quota.py
neutronclient/neutron/v2_0/rbac.py
neutronclient/neutron/v2_0/router.py
neutronclient/neutron/v2_0/securitygroup.py
neutronclient/neutron/v2_0/servicetype.py
neutronclient/neutron/v2_0/subnet.py
neutronclient/neutron/v2_0/subnetpool.py
neutronclient/neutron/v2_0/tag.py
neutronclient/neutron/v2_0/bgp/__init__.py
neutronclient/neutron/v2_0/bgp/dragentscheduler.py
neutronclient/neutron/v2_0/bgp/peer.py
neutronclient/neutron/v2_0/bgp/speaker.py
rackspace_python_neutronclient.egg-info/PKG-INFO
rackspace_python_neutronclient.egg-info/SOURCES.txt
rackspace_python_neutronclient.egg-info/dependency_links.txt
rackspace_python_neutronclient.egg-info/entry_points.txt
rackspace_python_neutronclient.egg-info/not-zip-safe
rackspace_python_neutronclient.egg-info/pbr.json
rackspace_python_neutronclient.egg-info/requires.txt
rackspace_python_neutronclient.egg-info/top_level.txt
